huaweicloudsdkgaussdb/__init__.py
huaweicloudsdkgaussdb/v3/__init__.py
huaweicloudsdkgaussdb/v3/gaussdb_async_client.py
huaweicloudsdkgaussdb/v3/gaussdb_client.py
huaweicloudsdkgaussdb/v3/model/__init__.py
huaweicloudsdkgaussdb/v3/model/access_control_rule.py
huaweicloudsdkgaussdb/v3/model/add_database_permission_request.py
huaweicloudsdkgaussdb/v3/model/add_database_permission_response.py
huaweicloudsdkgaussdb/v3/model/applicable_instances.py
huaweicloudsdkgaussdb/v3/model/apply_configuration_request_body.py
huaweicloudsdkgaussdb/v3/model/audit_log_detail.py
huaweicloudsdkgaussdb/v3/model/audit_log_download_link_request_body.py
huaweicloudsdkgaussdb/v3/model/auto_scaling_record_info.py
huaweicloudsdkgaussdb/v3/model/auto_scaling_switch_status.py
huaweicloudsdkgaussdb/v3/model/auto_sql_limiting_log.py
huaweicloudsdkgaussdb/v3/model/auto_sql_limiting_rule.py
huaweicloudsdkgaussdb/v3/model/backup.py
huaweicloudsdkgaussdb/v3/model/backup_encrypt_request.py
huaweicloudsdkgaussdb/v3/model/backup_policy.py
huaweicloudsdkgaussdb/v3/model/backups.py
huaweicloudsdkgaussdb/v3/model/batch_delete_backup_request.py
huaweicloudsdkgaussdb/v3/model/batch_delete_backup_request_body.py
huaweicloudsdkgaussdb/v3/model/batch_delete_backup_response.py
huaweicloudsdkgaussdb/v3/model/batch_operate_instance_tag_request_body.py
huaweicloudsdkgaussdb/v3/model/batch_tag_action_request.py
huaweicloudsdkgaussdb/v3/model/batch_tag_action_response.py
huaweicloudsdkgaussdb/v3/model/batch_upgrade_databases_request.py
huaweicloudsdkgaussdb/v3/model/batch_upgrade_databases_request_body.py
huaweicloudsdkgaussdb/v3/model/batch_upgrade_databases_response.py
huaweicloudsdkgaussdb/v3/model/cancel_gauss_my_sql_instance_eip_request.py
huaweicloudsdkgaussdb/v3/model/cancel_gauss_my_sql_instance_eip_response.py
huaweicloudsdkgaussdb/v3/model/cancel_schedule_task.py
huaweicloudsdkgaussdb/v3/model/cancel_schedule_task_request.py
huaweicloudsdkgaussdb/v3/model/cancel_schedule_task_response.py
huaweicloudsdkgaussdb-3.1.184.dist-info/METADATA
huaweicloudsdkgaussdb-3.1.184.dist-info/WHEEL
huaweicloudsdkgaussdb-3.1.184.dist-info/licenses/LICENSE
huaweicloudsdkgaussdb-3.1.184.dist-info/RECORD
